Metadata-Version: 2.1
Name: IFS-explorer
Version: 1.0.3
Summary: A python3 interactive visualization tool for integral field spectroscopy data
Home-page: https://github.com/frosales258/IFS_explorer
Author: Rosales-Ortega F. F., Angel Perez A., Xolo Tlapanco N., Sánchez. S. F.
Author-email: frosales@cantab.net
License: MIT
Keywords: IFS,FITS Images,Astropy,3D cube
Platform: UNKNOWN
Classifier: Programming Language :: Python :: 3.8
